leaguenames.py
leaguenames-0.0.1.dist-info/LICENSE.txt
leaguenames-0.0.1.dist-info/METADATA
leaguenames-0.0.1.dist-info/WHEEL
leaguenames-0.0.1.dist-info/top_level.txt
leaguenames-0.0.1.dist-info/RECORD
