Metadata-Version: 2.1
Name: leaguenames
Version: 0.0.1
Summary: A library that turns league of legends champions ids to champions names.
Home-page: UNKNOWN
License: UNKNOWN
Platform: UNKNOWN
Classifier: Programming Language :: Python :: 3
Classifier: License :: OSI Approved :: MIT License
Classifier: Operating System :: OS Independent
Requires-Dist: requests
